{
  "Version": "1.0",
  "Folders": {
    "Folders": [
      {
        "Foldername": "C:\\Users\\besemerj\\Documents\\GitHub\\CoherentMeterConnection\\..\\PhoenixUnitTestingFiles\\TestDataFiles\\AppData_Local\\Coherent\\CLA.LIB 1.0\\Certificates",
        "Disabled": false
      },
      {
        "Foldername": "C:\\Users\\besemerj\\Documents\\GitHub\\PhoenixUnitTestingFiles\\TestDataFiles\\AppData_Local\\Coherent\\CLA.LIB 1.0\\MoreCertificates",
        "Disabled": false
      }
    ],
    "Count": 2
  },
  "PreviousLoadSaveFileDirectory": null
}